odoo10_addon_stock_lot_scrap-10.0.1.0.0-py2.7-nspkg.pth
odoo/addons/stock_lot_scrap/README.rst
odoo/addons/stock_lot_scrap/__init__.py
odoo/addons/stock_lot_scrap/__manifest__.py
odoo/addons/stock_lot_scrap/i18n/de.po
odoo/addons/stock_lot_scrap/i18n/es.po
odoo/addons/stock_lot_scrap/i18n/fr.po
odoo/addons/stock_lot_scrap/i18n/it.po
odoo/addons/stock_lot_scrap/i18n/sl.po
odoo/addons/stock_lot_scrap/models/__init__.py
odoo/addons/stock_lot_scrap/models/stock_scrap_lot.py
odoo/addons/stock_lot_scrap/static/description/icon.png
odoo/addons/stock_lot_scrap/tests/__init__.py
odoo/addons/stock_lot_scrap/tests/test_stock_lot_scrap.py
odoo10_addon_stock_lot_scrap-10.0.1.0.0.dist-info/DESCRIPTION.rst
odoo10_addon_stock_lot_scrap-10.0.1.0.0.dist-info/METADATA
odoo10_addon_stock_lot_scrap-10.0.1.0.0.dist-info/RECORD
odoo10_addon_stock_lot_scrap-10.0.1.0.0.dist-info/WHEEL
odoo10_addon_stock_lot_scrap-10.0.1.0.0.dist-info/metadata.json
odoo10_addon_stock_lot_scrap-10.0.1.0.0.dist-info/namespace_packages.txt
odoo10_addon_stock_lot_scrap-10.0.1.0.0.dist-info/top_level.txt
