Metadata-Version: 2.0
Name: odoo10-addon-stock-lot-scrap
Version: 10.0.1.0.0
Summary: This module adds a button in Production Lot/Serial Number view form to Scrap all products contained.
Home-page: https://github.com/OCA/stock-logistics-workflow
Author: Tecnativa,Odoo Community Association (OCA)
Author-email: support@odoo-community.org
License: AGPL-3
Platform: UNKNOWN
Classifier: Programming Language :: Python
Classifier: Framework :: Odoo
Classifier: License :: OSI Approved :: GNU Affero General Public License v3
Requires-Python: ~=2.7
Requires-Dist: odoo (<10.1dev,>=10.0)
